PyRExecd-0.3.3.data/scripts/PyRExecd.pyw
pyrexecd/__init__.py
pyrexecd/icons/PyRexec.ico
pyrexecd/icons/PyRexecConnected.ico
PyRExecd-0.3.3.dist-info/LICENSE.txt
PyRExecd-0.3.3.dist-info/METADATA
PyRExecd-0.3.3.dist-info/WHEEL
PyRExecd-0.3.3.dist-info/top_level.txt
PyRExecd-0.3.3.dist-info/RECORD
