Metadata-Version: 2.1
Name: PyRExecd
Version: 0.3.3
Summary: Standalone SSH server for Windows
Home-page: https://github.com/euske/pyrexecd
Author: Yusuke Shinyama
Author-email: yusuke@shinyama.jp
License: MIT
Platform: UNKNOWN
Classifier: Development Status :: 4 - Beta
Classifier: Environment :: Win32 (MS Windows)
Classifier: License :: OSI Approved :: MIT License
Classifier: Topic :: Utilities
License-File: LICENSE.txt
Requires-Dist: paramiko
Requires-Dist: pypiwin32
